slot_attention/__init__.py
slot_attention/adaptive_slot_wrapper.py
slot_attention/multi_head_slot_attention.py
slot_attention/slot_attention.py
slot_attention/slot_attention_experimental.py
slot_attention-1.4.0.dist-info/LICENSE
slot_attention-1.4.0.dist-info/METADATA
slot_attention-1.4.0.dist-info/WHEEL
slot_attention-1.4.0.dist-info/top_level.txt
slot_attention-1.4.0.dist-info/RECORD
