Metadata-Version: 2.1
Name: slot_attention
Version: 1.4.0
Summary: Implementation of Slot Attention in Pytorch
Home-page: https://github.com/lucidrains/slot-attention
Author: Phil Wang
Author-email: lucidrains@gmail.com
License: MIT
Keywords: attention,artificial intelligence
Classifier: Development Status :: 4 - Beta
Classifier: Intended Audience :: Developers
Classifier: Topic :: Scientific/Engineering :: Artificial Intelligence
Classifier: License :: OSI Approved :: MIT License
Classifier: Programming Language :: Python :: 3.6
License-File: LICENSE
Requires-Dist: einops >=0.8.0
Requires-Dist: torch
